dazed/__init__.py
dazed/confusion_matrix.py
dazed-1.0.3.dist-info/LICENSE
dazed-1.0.3.dist-info/WHEEL
dazed-1.0.3.dist-info/METADATA
dazed-1.0.3.dist-info/RECORD
