Metadata-Version: 2.1
Name: dazed
Version: 1.0.3
Summary: A confusion matrix package.
License: MIT
Author: calmdown13
Author-email: callum@callumdownie.com
Requires-Python: >=3.6.1,<4.0.0
Classifier: License :: OSI Approved :: MIT License
Classifier: Programming Language :: Python :: 3
Classifier: Programming Language :: Python :: 3.7
Classifier: Programming Language :: Python :: 3.8
Classifier: Programming Language :: Python :: 3.9
Classifier: Programming Language :: Python :: 3.10
Provides-Extra: pandas
Requires-Dist: numpy (>=1.19.5,<2.0.0)
Requires-Dist: pandas (>=1.1.5,<2.0.0); extra == "pandas"
Project-URL: Documentation, https://dazed.readthedocs.io
